{
  "sourceMovie": {
    "tmdbId": 1016121,
    "title": "Beautiful Disaster",
    "slug": "beautiful-disaster",
    "year": 2023,
    "genres": [
      "Romance",
      "Drama",
      "Comedy"
    ],
    "whyPeopleLoveIt": "Beautiful Disaster (2023) stuck because it commits to its romance premise without apologizing—viewers remember set pieces and momentum as much as plot. Roger Kumble's control of tone keeps the ride coherent. The romance and drama blend is the engine: it lets the film shift registers without feeling like two different movies stitched together.",
    "vibes": [
      "romance",
      "drama",
      "comedy",
      "divisive"
    ]
  },
  "recommendations": [
    {
      "tmdbId": 9410,
      "title": "Great Expectations",
      "year": 1998,
      "matchPercentage": 96,
      "whyYoullLoveIt": "If Beautiful Disaster clicked for you, Great Expectations (1998) is a strong next stop: both trade in romance and drama, with comic timing and sharper banter. Expect a different story, but a similar willingness to go big when the moment demands it.",
      "sharedVibes": [
        "romance",
        "drama",
        "comedy"
      ],
      "mood": "funny"
    },
    {
      "tmdbId": 537915,
      "title": "After",
      "year": 2019,
      "matchPercentage": 94,
      "whyYoullLoveIt": "If Beautiful Disaster clicked for you, After (2019) is a strong next stop: both trade in romance and drama, with emotional whiplash that feels honest. Expect a different story, but a similar willingness to go big when the moment demands it.",
      "sharedVibes": [
        "romance",
        "drama"
      ],
      "mood": "bittersweet"
    },
    {
      "tmdbId": 9388,
      "title": "Thank You for Smoking",
      "year": 2005,
      "matchPercentage": 92,
      "whyYoullLoveIt": "If Beautiful Disaster clicked for you, Thank You for Smoking (2005) is a strong next stop: both trade in drama and comedy, with comic timing and sharper banter. Expect a different story, but a similar willingness to go big when the moment demands it.",
      "sharedVibes": [
        "drama",
        "comedy"
      ],
      "mood": "funny"
    },
    {
      "tmdbId": 845659,
      "title": "Perfect Addiction",
      "year": 2023,
      "matchPercentage": 90,
      "whyYoullLoveIt": "If Beautiful Disaster clicked for you, Perfect Addiction (2023) is a strong next stop: both trade in romance and drama, with emotional whiplash that feels honest. Expect a different story, but a similar willingness to go big when the moment demands it.",
      "sharedVibes": [
        "romance",
        "drama"
      ],
      "mood": "bittersweet"
    },
    {
      "tmdbId": 9362,
      "title": "Tremors",
      "year": 1990,
      "matchPercentage": 88,
      "whyYoullLoveIt": "If Beautiful Disaster clicked for you, Tremors (1990) is a strong next stop: both trade in comedy, with unease that lingers after the credits. Expect a different story, but a similar willingness to go big when the moment demands it.",
      "sharedVibes": [
        "comedy",
        "horror",
        "action",
        "science-fiction"
      ],
      "mood": "dark"
    },
    {
      "tmdbId": 9361,
      "title": "The Last of the Mohicans",
      "year": 1992,
      "matchPercentage": 86,
      "whyYoullLoveIt": "If Beautiful Disaster clicked for you, The Last of the Mohicans (1992) is a strong next stop: both trade in romance, with momentum and clean stakes. Expect a different story, but a similar willingness to go big when the moment demands it.",
      "sharedVibes": [
        "romance",
        "action",
        "history",
        "war"
      ],
      "mood": "tense"
    },
    {
      "tmdbId": 6415,
      "title": "Three Kings",
      "year": 1999,
      "matchPercentage": 84,
      "whyYoullLoveIt": "If Beautiful Disaster clicked for you, Three Kings (1999) is a strong next stop: both trade in comedy, with comic timing and sharper banter. Expect a different story, but a similar willingness to go big when the moment demands it.",
      "sharedVibes": [
        "comedy",
        "action",
        "war"
      ],
      "mood": "funny"
    },
    {
      "tmdbId": 9437,
      "title": "Kiss the Girls",
      "year": 1997,
      "matchPercentage": 82,
      "whyYoullLoveIt": "If Beautiful Disaster clicked for you, Kiss the Girls (1997) is a strong next stop: both trade in drama, with unease that lingers after the credits. Expect a different story, but a similar willingness to go big when the moment demands it.",
      "sharedVibes": [
        "drama",
        "thriller",
        "crime",
        "mystery"
      ],
      "mood": "dark"
    },
    {
      "tmdbId": 9331,
      "title": "Clear and Present Danger",
      "year": 1994,
      "matchPercentage": 80,
      "whyYoullLoveIt": "If Beautiful Disaster clicked for you, Clear and Present Danger (1994) is a strong next stop: both trade in drama, with momentum and clean stakes. Expect a different story, but a similar willingness to go big when the moment demands it.",
      "sharedVibes": [
        "drama",
        "action",
        "thriller"
      ],
      "mood": "tense"
    },
    {
      "tmdbId": 9344,
      "title": "Kids",
      "year": 1995,
      "matchPercentage": 78,
      "whyYoullLoveIt": "If Beautiful Disaster clicked for you, Kids (1995) is a strong next stop: both trade in drama, with momentum and clean stakes. Expect a different story, but a similar willingness to go big when the moment demands it.",
      "sharedVibes": [
        "drama",
        "crime"
      ],
      "mood": "tense"
    }
  ],
  "faq": [
    {
      "question": "What should I watch after Beautiful Disaster?",
      "answer": "Try Great Expectations, After, Thank You for Smoking—each shares DNA with Beautiful Disaster while changing the setting enough to feel fresh."
    },
    {
      "question": "What genre is Beautiful Disaster?",
      "answer": "Beautiful Disaster (2023) is best described as Romance, Drama, Comedy. Stores and algorithms use different labels, but that mix is what fans actually recognize on a rewatch."
    },
    {
      "question": "Is Beautiful Disaster part of a franchise?",
      "answer": "Yes—it's part of the \"Beautiful Disaster Collection\" storyline. You can enjoy it standalone, but sequels and tie-ins build on characters and continuity established here."
    }
  ],
  "relatedPages": [
    "10-things-i-hate-about-you",
    "17-again",
    "500-days-of-summer",
    "a-dogs-will",
    "a-drama-of-jealousy-and-other-things",
    "annie-hall",
    "anora"
  ]
}