{
  "sourceMovie": {
    "tmdbId": 294254,
    "title": "Maze Runner: The Scorch Trials",
    "slug": "maze-runner-the-scorch-trials",
    "year": 2015,
    "genres": [
      "Science Fiction",
      "Action",
      "Thriller",
      "Adventure"
    ],
    "whyPeopleLoveIt": "Audiences latched onto Maze Runner: The Scorch Trials (2015) as a science fiction theatrical experience: big enough for a group watch, specific enough to reward a second viewing once you know where it's headed. The science fiction and action blend is the engine: it lets the film shift registers without feeling like two different movies stitched together.",
    "vibes": [
      "science-fiction",
      "action",
      "thriller",
      "adventure",
      "divisive"
    ]
  },
  "recommendations": [
    {
      "tmdbId": 336843,
      "title": "Maze Runner: The Death Cure",
      "year": 2018,
      "matchPercentage": 96,
      "whyYoullLoveIt": "The filmmakers behind Maze Runner: The Death Cure (2018) clearly understood what makes science-fiction work — the same quality that keeps Maze Runner: The Scorch Trials rewatchable. Expect the same tense rhythm, executed with a fresh angle.",
      "sharedVibes": [
        "science-fiction",
        "action",
        "thriller",
        "adventure"
      ],
      "mood": "tense"
    },
    {
      "tmdbId": 76341,
      "title": "Mad Max: Fury Road",
      "year": 2015,
      "matchPercentage": 94,
      "whyYoullLoveIt": "Mad Max: Fury Road (2015) is the kind of film Maze Runner: The Scorch Trials fans discover and immediately send to their group chat. The science-fiction overlap is real, but it's the tense emotional pull that seals the recommendation.",
      "sharedVibes": [
        "science-fiction",
        "action",
        "adventure"
      ],
      "mood": "tense"
    },
    {
      "tmdbId": 198663,
      "title": "The Maze Runner",
      "year": 2014,
      "matchPercentage": 92,
      "whyYoullLoveIt": "The Maze Runner shares Maze Runner: The Scorch Trials's gift for science-fiction — the 2014 film delivers action without overstaying its welcome. Consider it required viewing once you've finished rewatching your first pick.",
      "sharedVibes": [
        "science-fiction",
        "action",
        "thriller",
        "mystery"
      ],
      "mood": "tense"
    },
    {
      "tmdbId": 72190,
      "title": "World War Z",
      "year": 2013,
      "matchPercentage": 90,
      "whyYoullLoveIt": "Much of what makes Maze Runner: The Scorch Trials compelling — the science-fiction, the action — shows up in World War Z (2013) in a slightly different form. Both films understand that dark storytelling works best when it trusts the audience.",
      "sharedVibes": [
        "science-fiction",
        "action",
        "thriller",
        "horror"
      ],
      "mood": "dark"
    },
    {
      "tmdbId": 280,
      "title": "Terminator 2: Judgment Day",
      "year": 1991,
      "matchPercentage": 88,
      "whyYoullLoveIt": "The science-fiction energy of Maze Runner: The Scorch Trials is alive in Terminator 2: Judgment Day (1991), filtered through a different story but the same emotional register. It earns its place on this list with a tense payoff that rivals the original pick.",
      "sharedVibes": [
        "science-fiction",
        "action",
        "thriller"
      ],
      "mood": "tense"
    },
    {
      "tmdbId": 157350,
      "title": "Divergent",
      "year": 2014,
      "matchPercentage": 86,
      "whyYoullLoveIt": "Divergent (2014) operates in the same science-fiction as Maze Runner: The Scorch Trials, but with its own distinct voice and pacing. The tense payoff will feel satisfyingly familiar without retreading the same ground.",
      "sharedVibes": [
        "science-fiction",
        "action",
        "adventure"
      ],
      "mood": "tense"
    },
    {
      "tmdbId": 262500,
      "title": "Insurgent",
      "year": 2015,
      "matchPercentage": 84,
      "whyYoullLoveIt": "Insurgent (2015) belongs to the same conversation as Maze Runner: The Scorch Trials — both anchor their science-fiction in action emotion that doesn't let go. The tense undercurrent connects them more than any plot summary would suggest.",
      "sharedVibes": [
        "science-fiction",
        "action",
        "thriller"
      ],
      "mood": "tense"
    },
    {
      "tmdbId": 74,
      "title": "War of the Worlds",
      "year": 2005,
      "matchPercentage": 82,
      "whyYoullLoveIt": "If Maze Runner: The Scorch Trials's science-fiction stayed with you, War of the Worlds (2005) delivers the same sensation through an entirely different story. The thriller through-line is the real common thread between them.",
      "sharedVibes": [
        "science-fiction",
        "thriller",
        "adventure"
      ],
      "mood": "tense"
    },
    {
      "tmdbId": 11234,
      "title": "The Omega Man",
      "year": 1971,
      "matchPercentage": 80,
      "whyYoullLoveIt": "Where Maze Runner: The Scorch Trials excels in science-fiction, The Omega Man (1971) doubles down on action to comparable effect. The tonal similarities run deep enough that watching both back-to-back feels intentional.",
      "sharedVibes": [
        "science-fiction",
        "action",
        "thriller",
        "drama"
      ],
      "mood": "tense"
    },
    {
      "tmdbId": 6479,
      "title": "I Am Legend",
      "year": 2007,
      "matchPercentage": 78,
      "whyYoullLoveIt": "I Am Legend (2007) is the natural next step after Maze Runner: The Scorch Trials: same science-fiction DNA, different perspective. The tense streak and thriller elevate it well above a simple genre exercise.",
      "sharedVibes": [
        "science-fiction",
        "thriller",
        "drama"
      ],
      "mood": "tense"
    }
  ],
  "faq": [
    {
      "question": "What should I watch after Maze Runner: The Scorch Trials?",
      "answer": "Try Maze Runner: The Death Cure, Mad Max: Fury Road, The Maze Runner—each shares DNA with Maze Runner: The Scorch Trials while changing the setting enough to feel fresh."
    },
    {
      "question": "What genre is Maze Runner: The Scorch Trials?",
      "answer": "Maze Runner: The Scorch Trials (2015) is best described as Science Fiction, Action, Thriller, Adventure. Stores and algorithms use different labels, but that mix is what fans actually recognize on a rewatch."
    },
    {
      "question": "Is Maze Runner: The Scorch Trials part of a franchise?",
      "answer": "Yes—it's part of the \"The Maze Runner Collection\" storyline. You can enjoy it standalone, but sequels and tie-ins build on characters and continuity established here."
    }
  ],
  "relatedPages": [
    "armageddon",
    "greenland",
    "jurassic-world",
    "jurassic-world-fallen-kingdom",
    "mad-max",
    "maze-runner-the-death-cure",
    "moonraker"
  ]
}