{
  "sourceMovie": {
    "tmdbId": 209262,
    "title": "Parkland",
    "slug": "parkland",
    "year": 2013,
    "genres": [
      "History",
      "Drama"
    ],
    "whyPeopleLoveIt": "People revisit Parkland for the same reason it broke through in 2013: clear stakes, memorable faces, and a drama rhythm that doesn't stall in the middle. Peter Landesman keeps the ensemble pointed in one direction. The history and drama blend is the engine: it lets the film shift registers without feeling like two different movies stitched together.",
    "vibes": [
      "history",
      "drama",
      "divisive"
    ]
  },
  "recommendations": [
    {
      "tmdbId": 152532,
      "title": "Dallas Buyers Club",
      "year": 2013,
      "matchPercentage": 96,
      "whyYoullLoveIt": "If Parkland clicked for you, Dallas Buyers Club (2013) is a strong next stop: both trade in history and drama, with momentum and clean stakes. Expect a different story, but a similar willingness to go big when the moment demands it.",
      "sharedVibes": [
        "history",
        "drama"
      ],
      "mood": "tense"
    },
    {
      "tmdbId": 3131,
      "title": "Gangs of New York",
      "year": 2002,
      "matchPercentage": 94,
      "whyYoullLoveIt": "If Parkland clicked for you, Gangs of New York (2002) is a strong next stop: both trade in history and drama, with momentum and clean stakes. Expect a different story, but a similar willingness to go big when the moment demands it.",
      "sharedVibes": [
        "history",
        "drama",
        "crime"
      ],
      "mood": "tense"
    },
    {
      "tmdbId": 261023,
      "title": "Black Mass",
      "year": 2015,
      "matchPercentage": 92,
      "whyYoullLoveIt": "If Parkland clicked for you, Black Mass (2015) is a strong next stop: both trade in history and drama, with momentum and clean stakes. Expect a different story, but a similar willingness to go big when the moment demands it.",
      "sharedVibes": [
        "history",
        "drama",
        "crime"
      ],
      "mood": "tense"
    },
    {
      "tmdbId": 292011,
      "title": "Richard Jewell",
      "year": 2019,
      "matchPercentage": 90,
      "whyYoullLoveIt": "If Parkland clicked for you, Richard Jewell (2019) is a strong next stop: both trade in history and drama, with momentum and clean stakes. Expect a different story, but a similar willingness to go big when the moment demands it.",
      "sharedVibes": [
        "history",
        "drama"
      ],
      "mood": "tense"
    },
    {
      "tmdbId": 88794,
      "title": "J. Edgar",
      "year": 2011,
      "matchPercentage": 88,
      "whyYoullLoveIt": "If Parkland clicked for you, J. Edgar (2011) is a strong next stop: both trade in history and drama, with momentum and clean stakes. Expect a different story, but a similar willingness to go big when the moment demands it.",
      "sharedVibes": [
        "history",
        "drama",
        "crime"
      ],
      "mood": "tense"
    },
    {
      "tmdbId": 4169,
      "title": "Breach",
      "year": 2007,
      "matchPercentage": 86,
      "whyYoullLoveIt": "If Parkland clicked for you, Breach (2007) is a strong next stop: both trade in history and drama, with unease that lingers after the credits. Expect a different story, but a similar willingness to go big when the moment demands it.",
      "sharedVibes": [
        "history",
        "drama",
        "thriller",
        "crime"
      ],
      "mood": "dark"
    },
    {
      "tmdbId": 245700,
      "title": "Mr. Turner",
      "year": 2014,
      "matchPercentage": 84,
      "whyYoullLoveIt": "If Parkland clicked for you, Mr. Turner (2014) is a strong next stop: both trade in history and drama, with momentum and clean stakes. Expect a different story, but a similar willingness to go big when the moment demands it.",
      "sharedVibes": [
        "history",
        "drama"
      ],
      "mood": "tense"
    },
    {
      "tmdbId": 649394,
      "title": "Worth",
      "year": 2021,
      "matchPercentage": 82,
      "whyYoullLoveIt": "If Parkland clicked for you, Worth (2021) is a strong next stop: both trade in history and drama, with momentum and clean stakes. Expect a different story, but a similar willingness to go big when the moment demands it.",
      "sharedVibes": [
        "history",
        "drama"
      ],
      "mood": "tense"
    },
    {
      "tmdbId": 716594,
      "title": "No Man of God",
      "year": 2021,
      "matchPercentage": 80,
      "whyYoullLoveIt": "If Parkland clicked for you, No Man of God (2021) is a strong next stop: both trade in history and drama, with unease that lingers after the credits. Expect a different story, but a similar willingness to go big when the moment demands it.",
      "sharedVibes": [
        "history",
        "drama",
        "crime",
        "thriller"
      ],
      "mood": "dark"
    },
    {
      "tmdbId": 1417,
      "title": "Pan's Labyrinth",
      "year": 2006,
      "matchPercentage": 78,
      "whyYoullLoveIt": "If Parkland clicked for you, Pan's Labyrinth (2006) is a strong next stop: both trade in drama, with momentum and clean stakes. Expect a different story, but a similar willingness to go big when the moment demands it.",
      "sharedVibes": [
        "drama",
        "fantasy",
        "war"
      ],
      "mood": "tense"
    }
  ],
  "faq": [
    {
      "question": "What should I watch after Parkland?",
      "answer": "Try Dallas Buyers Club, Gangs of New York, Black Mass—each shares DNA with Parkland while changing the setting enough to feel fresh."
    },
    {
      "question": "What genre is Parkland?",
      "answer": "Parkland (2013) is best described as History, Drama. Stores and algorithms use different labels, but that mix is what fans actually recognize on a rewatch."
    },
    {
      "question": "Is Parkland worth revisiting?",
      "answer": "Viewer scores sit around 6.2/10 on TMDB—high enough that replays are common for people who like this history lane."
    }
  ],
  "relatedPages": [
    "12-strong",
    "12-years-a-slave",
    "13-hours-the-secret-soldiers-of-benghazi",
    "a-beautiful-day-in-the-neighborhood",
    "a-bridge-too-far",
    "a-taxi-driver",
    "against-the-ice"
  ]
}