{
  "sourceMovie": {
    "tmdbId": 7980,
    "title": "The Lovely Bones",
    "slug": "the-lovely-bones",
    "year": 2009,
    "genres": [
      "Fantasy",
      "Drama"
    ],
    "whyPeopleLoveIt": "Audiences latched onto The Lovely Bones (2009) as a fantasy theatrical experience: big enough for a group watch, specific enough to reward a second viewing once you know where it's headed. The fantasy and drama blend is the engine: it lets the film shift registers without feeling like two different movies stitched together.",
    "vibes": [
      "fantasy",
      "drama",
      "rewatchable"
    ]
  },
  "recommendations": [
    {
      "tmdbId": 149509,
      "title": "Horns",
      "year": 2013,
      "matchPercentage": 96,
      "whyYoullLoveIt": "The fantasy energy of The Lovely Bones is alive in Horns (2013), filtered through a different story but the same emotional register. It earns its place on this list with a tense payoff that rivals the original pick.",
      "sharedVibes": [
        "fantasy",
        "drama",
        "thriller"
      ],
      "mood": "tense"
    },
    {
      "tmdbId": 120,
      "title": "The Lord of the Rings: The Fellowship of the Ring",
      "year": 2001,
      "matchPercentage": 94,
      "whyYoullLoveIt": "The Lord of the Rings: The Fellowship of the Ring (2001) operates in the same fantasy as The Lovely Bones, but with its own distinct voice and pacing. The tense payoff will feel satisfyingly familiar without retreading the same ground.",
      "sharedVibes": [
        "fantasy",
        "adventure",
        "action"
      ],
      "mood": "tense"
    },
    {
      "tmdbId": 346364,
      "title": "It",
      "year": 2017,
      "matchPercentage": 92,
      "whyYoullLoveIt": "It (2017) belongs to the same conversation as The Lovely Bones — both anchor their drama in horror emotion that doesn't let go. The dark undercurrent connects them more than any plot summary would suggest.",
      "sharedVibes": [
        "drama",
        "horror",
        "thriller"
      ],
      "mood": "dark"
    },
    {
      "tmdbId": 101,
      "title": "Léon: The Professional",
      "year": 1994,
      "matchPercentage": 90,
      "whyYoullLoveIt": "If The Lovely Bones's drama stayed with you, Léon: The Professional (1994) delivers the same sensation through an entirely different story. The crime through-line is the real common thread between them.",
      "sharedVibes": [
        "drama",
        "crime",
        "action"
      ],
      "mood": "tense"
    },
    {
      "tmdbId": 103,
      "title": "Taxi Driver",
      "year": 1976,
      "matchPercentage": 88,
      "whyYoullLoveIt": "Where The Lovely Bones excels in drama, Taxi Driver (1976) doubles down on crime to comparable effect. The tonal similarities run deep enough that watching both back-to-back feels intentional.",
      "sharedVibes": [
        "drama",
        "crime"
      ],
      "mood": "tense"
    },
    {
      "tmdbId": 340666,
      "title": "Nocturnal Animals",
      "year": 2016,
      "matchPercentage": 86,
      "whyYoullLoveIt": "Nocturnal Animals (2016) is the natural next step after The Lovely Bones: same drama DNA, different perspective. The tense streak and thriller elevate it well above a simple genre exercise.",
      "sharedVibes": [
        "drama",
        "thriller"
      ],
      "mood": "tense"
    },
    {
      "tmdbId": 184,
      "title": "Jackie Brown",
      "year": 1997,
      "matchPercentage": 84,
      "whyYoullLoveIt": "Fans of The Lovely Bones who respond to its drama will find Jackie Brown (1997) immediately familiar. Both films share a crime sensibility without ever feeling like carbon copies of each other.",
      "sharedVibes": [
        "drama",
        "crime",
        "thriller"
      ],
      "mood": "dark"
    },
    {
      "tmdbId": 235,
      "title": "Stand by Me",
      "year": 1986,
      "matchPercentage": 82,
      "whyYoullLoveIt": "There's a reason The Lovely Bones fans keep landing on Stand by Me (1986) — the drama is unmistakably related even when the plots diverge. Both films operate on the same emotional frequency, especially in their third acts.",
      "sharedVibes": [
        "drama",
        "crime"
      ],
      "mood": "tense"
    },
    {
      "tmdbId": 251,
      "title": "Ghost",
      "year": 1990,
      "matchPercentage": 80,
      "whyYoullLoveIt": "Ghost draws from the same fantasy well as The Lovely Bones, channeling thriller in ways that feel unmistakably related. The 1990 film makes a natural companion watch — similar in spirit but distinctly its own.",
      "sharedVibes": [
        "fantasy",
        "thriller",
        "romance"
      ],
      "mood": "tense"
    },
    {
      "tmdbId": 1598,
      "title": "Cape Fear",
      "year": 1991,
      "matchPercentage": 78,
      "whyYoullLoveIt": "Cape Fear (1991) laid groundwork for the tone and themes that The Lovely Bones later expanded. If The Lovely Bones resonated for you, this predecessor shows where that emotional DNA began.",
      "sharedVibes": [
        "drama",
        "crime",
        "thriller"
      ],
      "mood": "dark"
    }
  ],
  "faq": [
    {
      "question": "What should I watch after The Lovely Bones?",
      "answer": "Try Horns, The Lord of the Rings: The Fellowship of the Ring, It—each shares DNA with The Lovely Bones while changing the setting enough to feel fresh."
    },
    {
      "question": "What genre is The Lovely Bones?",
      "answer": "The Lovely Bones (2009) is best described as Fantasy, Drama. Stores and algorithms use different labels, but that mix is what fans actually recognize on a rewatch."
    },
    {
      "question": "Is The Lovely Bones worth revisiting?",
      "answer": "Viewer scores sit around 7.1/10 on TMDB—high enough that replays are common for people who like this fantasy lane."
    }
  ],
  "relatedPages": [
    "about-time",
    "along-with-the-gods-the-two-worlds",
    "babe",
    "big",
    "big-fish",
    "cinderella",
    "city-of-angels"
  ]
}